lapipe/__init__.py
lapipe-1.0.0.dist-info/METADATA
lapipe-1.0.0.dist-info/WHEEL
lapipe-1.0.0.dist-info/licenses/LICENSE
lapipe-1.0.0.dist-info/RECORD
