Metadata-Version: 2.4
Name: lapipe
Version: 1.0.0
Summary: Tiny value-first pipe operator with optional '_' placeholder
Project-URL: Homepage, https://github.com/MaximeRivest/lapipe
Project-URL: Issues, https://github.com/MaximeRivest/lapipe/issues
Author-email: Maxime Rivest <mrive052@gmail.com>
License-Expression: MIT
License-File: LICENSE
Classifier: License :: OSI Approved :: MIT License
Classifier: Operating System :: OS Independent
Classifier: Programming Language :: Python :: 3
Classifier: Topic :: Utilities
Requires-Python: >=3.8
